engine/__init__.py
engine/exceptions.py
engine/parser.py
engine/syntax.py
tools/__init__.py
tools/build.py
tools/clean.py
tools/live.py
web_ui/__init__.py
web_ui/main.py
IFProject-0.0.0.dist-info/LICENSE
IFProject-0.0.0.dist-info/METADATA
IFProject-0.0.0.dist-info/WHEEL
IFProject-0.0.0.dist-info/entry_points.txt
IFProject-0.0.0.dist-info/top_level.txt
IFProject-0.0.0.dist-info/RECORD
