Metadata-Version: 2.1
Name: IFProject
Version: 0.0.0
Summary: A Python package for creating Interactive Fiction Narratives!
Author-email: Max Suica <max.suica@gmail.com>, Kyle Hess <donotreply@github.com>
License: AGPLv3
Project-URL: Homepage, https://github.com/maxsu/IFProject
Keywords: IF,Interactive Fiction,PyScript
Classifier: Topic :: Games/Entertainment :: Role-Playing
Classifier: Intended Audience :: Developers
Classifier: License :: OSI Approved :: GNU Affero General Public License v3
Classifier: Natural Language :: English
Classifier: Programming Language :: Python :: 3.12
Classifier: Environment :: Web Environment
Classifier: Environment :: WebAssembly
Classifier: Operating System :: POSIX :: Linux
Classifier: Operating System :: MacOS :: MacOS X
Classifier: Operating System :: Microsoft :: Windows
Classifier: Operating System :: Android
Classifier: Operating System :: iOS
Requires-Python: >=3.12
License-File: LICENSE
Requires-Dist: build
Requires-Dist: twine
Requires-Dist: mkdocstrings-python
Requires-Dist: pydispatch
Requires-Dist: logging518
Requires-Dist: ruff
Requires-Dist: pytest
Requires-Dist: coverage
Requires-Dist: mypy
Requires-Dist: autohooks
Requires-Dist: autohooks-plugin-ruff
Requires-Dist: autohooks-plugin-pytest
Requires-Dist: autohooks-plugin-mypy
